{
  "indexes": [
    {
      "collectionGroup": "users",
      "queryScope": "COLLECTION",
      "fields": [
        {
          "fieldPath": "mbtiType",
          "order": "ASCENDING"
        },
        {
          "fieldPath": "updatedAt",
          "order": "DESCENDING"
        }
      ]
    },
    {
      "collectionGroup": "users",
      "queryScope": "COLLECTION",
      "fields": [
        {
          "fieldPath": "createdAt",
          "order": "DESCENDING"
        }
      ]
    },
    {
      "collectionGroup": "users",
      "queryScope": "COLLECTION",
      "fields": [
        {
          "fieldPath": "stats.lastLoginAt",
          "order": "DESCENDING"
        }
      ]
    },
    {
      "collectionGroup": "recommendations",
      "queryScope": "COLLECTION",
      "fields": [
        {
          "fieldPath": "userId",
          "order": "ASCENDING"
        },
        {
          "fieldPath": "createdAt",
          "order": "DESCENDING"
        }
      ]
    },
    {
      "collectionGroup": "recommendations",
      "queryScope": "COLLECTION",
      "fields": [
        {
          "fieldPath": "userId",
          "order": "ASCENDING"
        },
        {
          "fieldPath": "type",
          "order": "ASCENDING"
        },
        {
          "fieldPath": "createdAt",
          "order": "DESCENDING"
        }
      ]
    },
    {
      "collectionGroup": "recommendations",
      "queryScope": "COLLECTION",
      "fields": [
        {
          "fieldPath": "userId",
          "order": "ASCENDING"
        },
        {
          "fieldPath": "score",
          "order": "DESCENDING"
        }
      ]
    },
    {
      "collectionGroup": "chats",
      "queryScope": "COLLECTION",
      "fields": [
        {
          "fieldPath": "type",
          "order": "ASCENDING"
        },
        {
          "fieldPath": "updatedAt",
          "order": "DESCENDING"
        }
      ]
    },
    {
      "collectionGroup": "chats",
      "queryScope": "COLLECTION",
      "fields": [
        {
          "fieldPath": "targetMBTI",
          "arrayConfig": "CONTAINS"
        },
        {
          "fieldPath": "updatedAt",
          "order": "DESCENDING"
        }
      ]
    },
    {
      "collectionGroup": "chats",
      "queryScope": "COLLECTION",
      "fields": [
        {
          "fieldPath": "participants",
          "arrayConfig": "CONTAINS"
        },
        {
          "fieldPath": "updatedAt",
          "order": "DESCENDING"
        }
      ]
    },
    {
      "collectionGroup": "messages",
      "queryScope": "COLLECTION",
      "fields": [
        {
          "fieldPath": "chatId",
          "order": "ASCENDING"
        },
        {
          "fieldPath": "createdAt",
          "order": "ASCENDING"
        }
      ]
    },
    {
      "collectionGroup": "messages",
      "queryScope": "COLLECTION",
      "fields": [
        {
          "fieldPath": "chatId",
          "order": "ASCENDING"
        },
        {
          "fieldPath": "createdAt",
          "order": "DESCENDING"
        }
      ]
    },
    {
      "collectionGroup": "messages",
      "queryScope": "COLLECTION",
      "fields": [
        {
          "fieldPath": "senderId",
          "order": "ASCENDING"
        },
        {
          "fieldPath": "createdAt",
          "order": "DESCENDING"
        }
      ]
    },
    {
      "collectionGroup": "mbti_tests",
      "queryScope": "COLLECTION",
      "fields": [
        {
          "fieldPath": "userId",
          "order": "ASCENDING"
        },
        {
          "fieldPath": "completedAt",
          "order": "DESCENDING"
        }
      ]
    },
    {
      "collectionGroup": "mbti_tests",
      "queryScope": "COLLECTION",
      "fields": [
        {
          "fieldPath": "result",
          "order": "ASCENDING"
        },
        {
          "fieldPath": "completedAt",
          "order": "DESCENDING"
        }
      ]
    },
    {
      "collectionGroup": "user_activity_logs",
      "queryScope": "COLLECTION",
      "fields": [
        {
          "fieldPath": "userId",
          "order": "ASCENDING"
        },
        {
          "fieldPath": "timestamp",
          "order": "DESCENDING"
        }
      ]
    },
    {
      "collectionGroup": "user_activity_logs",
      "queryScope": "COLLECTION",
      "fields": [
        {
          "fieldPath": "userId",
          "order": "ASCENDING"
        },
        {
          "fieldPath": "action",
          "order": "ASCENDING"
        },
        {
          "fieldPath": "timestamp",
          "order": "DESCENDING"
        }
      ]
    },
    {
      "collectionGroup": "reports",
      "queryScope": "COLLECTION",
      "fields": [
        {
          "fieldPath": "targetType",
          "order": "ASCENDING"
        },
        {
          "fieldPath": "createdAt",
          "order": "DESCENDING"
        }
      ]
    },
    {
      "collectionGroup": "reports",
      "queryScope": "COLLECTION",
      "fields": [
        {
          "fieldPath": "reporterId",
          "order": "ASCENDING"
        },
        {
          "fieldPath": "createdAt",
          "order": "DESCENDING"
        }
      ]
    },
    {
      "collectionGroup": "blocked_users",
      "queryScope": "COLLECTION",
      "fields": [
        {
          "fieldPath": "blockerId",
          "order": "ASCENDING"
        },
        {
          "fieldPath": "createdAt",
          "order": "DESCENDING"
        }
      ]
    }
  ],
  "fieldOverrides": [
    {
      "collectionGroup": "users",
      "fieldPath": "email",
      "indexes": [
        {
          "order": "ASCENDING",
          "queryScope": "COLLECTION"
        }
      ]
    },
    {
      "collectionGroup": "users",
      "fieldPath": "mbtiType",
      "indexes": [
        {
          "order": "ASCENDING",
          "queryScope": "COLLECTION"
        }
      ]
    },
    {
      "collectionGroup": "chats",
      "fieldPath": "participants",
      "indexes": [
        {
          "arrayConfig": "CONTAINS",
          "queryScope": "COLLECTION"
        }
      ]
    },
    {
      "collectionGroup": "chats",
      "fieldPath": "targetMBTI",
      "indexes": [
        {
          "arrayConfig": "CONTAINS",
          "queryScope": "COLLECTION"
        }
      ]
    }
  ]
}
